{
    "AshuraGift1": {
        "name": "Striped Dace",
        "type": "Fish",
        "updated": 1717896106384
    },
    "AshuraGift2": {
        "name": "Golden Salmon",
        "type": "Fish",
        "updated": 1717896106384
    },
    "AshuraGift3": {
        "name": "Sernuk Noodle Stew",
        "type": "Dish",
        "updated": 1717896106384
    },
    "AshuraGift4": {
        "name": "Blueberry Pie",
        "type": "Dish",
        "updated": 1717896106384
    },
    "AuniGift1": {
        "name": "Common Field Cricket",
        "type": "Bug",
        "updated": 1717896106384
    },
    "AuniGift2": {
        "name": "Proudhorned Stag Beetle",
        "type": "Bug",
        "updated": 1717896106384
    },
    "AuniGift3": {
        "name": "Petit Fives",
        "type": "Dish",
        "updated": 1717896106384
    },
    "AuniGift4": {
        "name": "Celebration Cake",
        "type": "Dish",
        "updated": 1717896106384
    },
    "BadruuGift1": {
        "name": "Carrot Seed",
        "type": "Crop",
        "updated": 1717896106384
    },
    "BadruuGift2": {
        "name": "SpeedyGro Fertilizer",
        "type": "Crop",
        "updated": 1717896106384
    },
    "BadruuGift3": {
        "name": "Loaded Potato Soup",
        "type": "Dish",
        "updated": 1717896106384
    },
    "BadruuGift4": {
        "name": "Azure Stonehopper",
        "type": "Bug",
        "updated": 1717896106384
    },
    "CaleriGift1": {
        "name": "Grilled Mushroom",
        "type": "Dish",
        "updated": 1717896106384
    },
    "CaleriGift2": {
        "name": "Kilima Redfin",
        "type": "Fish",
        "updated": 1717896106384
    },
    "CaleriGift3": {
        "name": "Pinecone",
        "type": "Gatherable",
        "updated": 1717896106384
    },
    "CaleriGift4": {
        "name": "Dari Cloves",
        "type": "Gatherable",
        "updated": 1717896106384
    },
    "ChayneGift1": {
        "name": "Wild Ginger",
        "type": "Gatherable",
        "updated": 1717896106384
    },
    "ChayneGift2": {
        "name": "Wheat",
        "type": "Crop",
        "updated": 1717896106384
    },
    "ChayneGift3": {
        "name": "Cream of Tomato Soup",
        "type": "Dish",
        "updated": 1717896106384
    },
    "ChayneGift4": {
        "name": "Palian Onion Soup",
        "type": "Dish",
        "updated": 1717896106384
    },
    "DelailaGift1": {
        "name": "Rainbow Trout",
        "type": "Fish",
        "updated": 1717896106384
    },
    "DelailaGift2": {
        "name": "Kilima Catfish",
        "type": "Fish",
        "updated": 1717896106384
    },
    "DelailaGift3": {
        "name": "Shepp's Pie",
        "type": "Dish",
        "updated": 1717896106384
    },
    "DelailaGift4": {
        "name": "Gold Bar",
        "type": "Material",
        "updated": 1717896106384
    },
    "EinarGift1": {
        "name": "Bahari Crab",
        "type": "Bug",
        "updated": 1717896106384
    },
    "EinarGift2": {
        "name": "Prism Trout",
        "type": "Fish",
        "updated": 1717896106384
    },
    "EinarGift3": {
        "name": "Glow Worm",
        "type": "Equipment",
        "updated": 1717896106384
    },
    "EinarGift4": {
        "name": "Fisherman's Brew",
        "type": "Dish",
        "updated": 1717896106384
    },
    "ElouisaGift1": {
        "name": "Ship Fragments",
        "type": "Gatherable",
        "updated": 1717896106384
    },
    "ElouisaGift2": {
        "name": "Bahari Bee",
        "type": "Bug",
        "updated": 1717896106384
    },
    "ElouisaGift3": {
        "name": "Raspberry Beetle",
        "type": "Bug",
        "updated": 1717896106384
    },
    "ElouisaGift4": {
        "name": "Cloudfish",
        "type": "Fish",
        "updated": 1717896106384
    },
    "EsheGift1": {
        "name": "Grilled Oyster",
        "type": "Dish",
        "updated": 1717896106384
    },
    "EsheGift2": {
        "name": "Bluefin Tuna",
        "type": "Fish",
        "updated": 1717896106384
    },
    "EsheGift3": {
        "name": "Silver Ore",
        "type": "Material",
        "updated": 1717896106384
    },
    "EsheGift4": {
        "name": "Gold Ore",
        "type": "Material",
        "updated": 1717896106384
    },
    "HassianGift1": {
        "name": "Spotted Chapaa Tail",
        "type": "Gatherable",
        "updated": 1717896106384
    },
    "HassianGift2": {
        "name": "Sernuk Noodle Stew",
        "type": "Dish",
        "updated": 1717896106384
    },
    "HassianGift3": {
        "name": "Iron Bar",
        "type": "Material",
        "updated": 1717896106384
    },
    "HassianGift4": {
        "name": "Shimmerfin",
        "type": "Fish",
        "updated": 1717896106384
    },
    "HeklaGift1": {
        "name": "Grilled Fish",
        "type": "Dish",
        "updated": 1717896106384
    },
    "HeklaGift2": {
        "name": "Painted Perch",
        "type": "Fish",
        "updated": 1717896106384
    },
    "HeklaGift3": {
        "name": "Beluga",
        "type": "Fish",
        "updated": 1717896106384
    },
    "HeklaGift4": {
        "name": "Enchanted Pupfish",
        "type": "Fish",
        "updated": 1717896106384
    },
    "HodariGift1": {
        "name": "Fur",
        "type": "Gatherable",
        "updated": 1717896106384
    },
    "HodariGift2": {
        "name": "Striped Chapaa Tail",
        "type": "Gatherable",
        "updated": 1717896106384
    },
    "HodariGift3": {
        "name": "Iron Ore",
        "type": "Material",
        "updated": 1717896106384
    },
    "HodariGift4": {
        "name": "Firebreathing Dragonfly",
        "type": "Bug",
        "updated": 1717896106384
    },
    "JelGift1": {
        "name": "Shell",
        "type": "Gatherable",
        "updated": 1717896106384
    },
    "JelGift2": {
        "name": "Albino Eel",
        "type": "Fish",
        "updated": 1717896106384
    },
    "JelGift3": {
        "name": "Pearl",
        "type": "Gatherable",
        "updated": 1717896106384
    },
    "JelGift4": {
        "name": "Green Pearl",
        "type": "Gatherable",
        "updated": 1717896106384
    },
    "JinaGift1": {
        "name": "Coral",
        "type": "Gatherable",
        "updated": 1717896106384
    },
    "JinaGift2": {
        "name": "Duskwing Butterfly",
        "type": "Bug",
        "updated": 1717896106384
    },
    "JinaGift3": {
        "name": "Dragon's Beard Peat",
        "type": "Gatherable",
        "updated": 1717896106384
    },
    "JinaGift4": {
        "name": "Celebration Cake",
        "type": "Dish",
        "updated": 1717896106384
    },
    "KenliGift1": {
        "name": "Wagon Wheel",
        "type": "Gatherable",
        "updated": 1717896106384
    },
    "KenliGift2": {
        "name": "Fish Stew",
        "type": "Dish",
        "updated": 1717896106384
    },
    "KenliGift3": {
        "name": "Oysters Akwinduu",
        "type": "Dish",
        "updated": 1717896106384
    },
    "KenliGift4": {
        "name": "Bouillabaisse",
        "type": "Dish",
        "updated": 1717896106384
    },
    "KenyattaGift1": {
        "name": "Barracuda",
        "type": "Fish",
        "updated": 1717896106384
    },
    "KenyattaGift2": {
        "name": "Pickled Onions",
        "type": "Cooking Product",
        "updated": 1717896106384
    },
    "KenyattaGift3": {
        "name": "Banded Muujin Mane",
        "type": "Material",
        "updated": 1717896106384
    },
    "KenyattaGift4": {
        "name": "Crimson Fangtooth",
        "type": "Fish",
        "updated": 1717896106384
    },
    "Nai'OGift1": {
        "name": "Spice Sprouts",
        "type": "Gatherable",
        "updated": 1717896106384
    },
    "Nai'OGift2": {
        "name": "QualityUp Fertilizer",
        "type": "Crop",
        "updated": 1717896106384
    },
    "Nai'OGift3": {
        "name": "Blueberry Jam",
        "type": "Cooking Product",
        "updated": 1717896106384
    },
    "Nai'OGift4": {
        "name": "Steak Dinner",
        "type": "Dish",
        "updated": 1717896106384
    },
    "NajumaGift1": {
        "name": "Clay",
        "type": "Material",
        "updated": 1717896106384
    },
    "NajumaGift2": {
        "name": "Copper Bar",
        "type": "Material",
        "updated": 1717896106384
    },
    "NajumaGift3": {
        "name": "Iron Ore",
        "type": "Material",
        "updated": 1717896106384
    },
    "NajumaGift4": {
        "name": "Silver Bar",
        "type": "Material",
        "updated": 1717896106384
    },
    "RethGift1": {
        "name": "Potato",
        "type": "Crop",
        "updated": 1717896106384
    },
    "RethGift2": {
        "name": "Sernuk Noodle Stew",
        "type": "Dish",
        "updated": 1717896106384
    },
    "RethGift3": {
        "name": "Apple",
        "type": "Crop",
        "updated": 1717896106384
    },
    "RethGift4": {
        "name": "Palian Onion Soup",
        "type": "Dish",
        "updated": 1717896106384
    },
    "SifuuGift1": {
        "name": "Muujin Meat",
        "type": "Cooking Product",
        "updated": 1717896106384
    },
    "SifuuGift2": {
        "name": "Pickled Carrots",
        "type": "Cooking Product",
        "updated": 1717896106384
    },
    "SifuuGift3": {
        "name": "Silver Ore",
        "type": "Material",
        "updated": 1717896106384
    },
    "SifuuGift4": {
        "name": "Swordfin Eel",
        "type": "Fish",
        "updated": 1717896106384
    },
    "SubiraGift1": {
        "name": "Potato",
        "type": "Crop",
        "updated": 1717896106384
    },
    "SubiraGift2": {
        "name": "Steak Dinner",
        "type": "Dish",
        "updated": 1717896106384
    },
    "SubiraGift3": {
        "name": "Ancient Amber Beetle",
        "type": "Bug",
        "updated": 1717896106384
    },
    "SubiraGift4": {
        "name": "Spicy Rice Cakes",
        "type": "Dish",
        "updated": 1717896106384
    },
    "TamalaGift1": {
        "name": "Fur",
        "type": "Gatherable",
        "updated": 1717896106384
    },
    "TamalaGift2": {
        "name": "Garden Millipede",
        "type": "Bug",
        "updated": 1717896106384
    },
    "TamalaGift3": {
        "name": "Hairy Millipede",
        "type": "Bug",
        "updated": 1717896106384
    },
    "TamalaGift4": {
        "name": "Long Nosed Unicorn Fish",
        "type": "Fish",
        "updated": 1717896106384
    },
    "TauGift1": {
        "name": "Sapwood Plank",
        "type": "Material",
        "updated": 1717896106384
    },
    "TauGift2": {
        "name": "Unopened Oyster",
        "type": "Gatherable",
        "updated": 1717896106384
    },
    "TauGift3": {
        "name": "Brighteye Butterfly",
        "type": "Bug",
        "updated": 1717896106384
    },
    "TauGift4": {
        "name": "Wagon Wheel",
        "type": "Gatherable",
        "updated": 1717896106384
    },
    "TishGift1": {
        "name": "Wagon Wheel",
        "type": "Gatherable",
        "updated": 1717896106384
    },
    "TishGift2": {
        "name": "Juniper Seed",
        "type": "Crop",
        "updated": 1717896106384
    },
    "TishGift3": {
        "name": "Pinecone",
        "type": "Gatherable",
        "updated": 1717896106384
    },
    "TishGift4": {
        "name": "Blueberry Pie",
        "type": "Dish",
        "updated": 1717896106384
    },
    "ZekiGift1": {
        "name": "Silver Salmon",
        "type": "Fish",
        "updated": 1717896106384
    },
    "ZekiGift2": {
        "name": "Golden Salmon",
        "type": "Fish",
        "updated": 1717896106384
    },
    "ZekiGift3": {
        "name": "Oysters Akwinduu",
        "type": "Dish",
        "updated": 1717896106384
    },
    "ZekiGift4": {
        "name": "Gold Ore",
        "type": "Material",
        "updated": 1717896106384
    }
}